fastapi_new-0.0.4.dist-info/METADATA
fastapi_new-0.0.4.dist-info/WHEEL
fastapi_new-0.0.4.dist-info/entry_points.txt
fastapi_new-0.0.4.dist-info/licenses/LICENSE
fastapi_new/__init__.py
fastapi_new/__main__.py
fastapi_new/cli.py
fastapi_new/new.py
fastapi_new/py.typed
fastapi_new/utils/cli.py
fastapi_new-0.0.4.dist-info/RECORD
