Metadata-Version: 2.4
Name: fastapi-new
Version: 0.0.4
Summary: Create a new FastAPI project in one command
Author-Email: =?utf-8?q?Sebasti=C3=A1n_Ram=C3=ADrez?= <tiangolo@gmail.com>
License-Expression: MIT
License-File: LICENSE
Classifier: Intended Audience :: Information Technology
Classifier: Intended Audience :: System Administrators
Classifier: Operating System :: OS Independent
Classifier: Programming Language :: Python :: 3
Classifier: Programming Language :: Python
Classifier: Topic :: Internet
Classifier: Topic :: Software Development :: Libraries :: Application Frameworks
Classifier: Topic :: Software Development :: Libraries :: Python Modules
Classifier: Topic :: Software Development :: Libraries
Classifier: Topic :: Software Development
Classifier: Typing :: Typed
Classifier: Development Status :: 4 - Beta
Classifier: Intended Audience :: Developers
Classifier: Programming Language :: Python :: 3 :: Only
Classifier: Programming Language :: Python :: 3.10
Classifier: Programming Language :: Python :: 3.11
Classifier: Programming Language :: Python :: 3.12
Classifier: Programming Language :: Python :: 3.13
Classifier: Programming Language :: Python :: 3.14
Project-URL: Homepage, https://github.com/fastapi/fastapi-new
Project-URL: Documentation, https://github.com/fastapi/fastapi-new
Project-URL: Repository, https://github.com/fastapi/fastapi-new
Project-URL: Issues, https://github.com/fastapi/fastapi-new/issues
Project-URL: Changelog, https://github.com/fastapi/fastapi-new/release-notes.md
Requires-Python: >=3.10
Requires-Dist: prek<1.0.0,>=0.2.24
Requires-Dist: typer>=0.12.0
Requires-Dist: rich>=13.0.0
Requires-Dist: typing-extensions>=4.8.0
Requires-Dist: rich-toolkit>=0.15.1
Provides-Extra: dev
Requires-Dist: pytest>=8.0.0; extra == "dev"
Requires-Dist: coverage[toml]>=7.0.0; extra == "dev"
Requires-Dist: mypy>=1.8.0; extra == "dev"
Requires-Dist: ruff>=0.3.0; extra == "dev"
